fw_heudiconv/__init__.py
fw_heudiconv/backend_funcs/__init__.py
fw_heudiconv/backend_funcs/convert.py
fw_heudiconv/backend_funcs/query.py
fw_heudiconv/backend_funcs/utils.py
fw_heudiconv/cli/__init__.py
fw_heudiconv/cli/clear.py
fw_heudiconv/cli/curate.py
fw_heudiconv/cli/export.py
fw_heudiconv/cli/meta.py
fw_heudiconv/cli/reproin_check.py
fw_heudiconv/cli/tabulate.py
fw_heudiconv/cli/validate.py
fw_heudiconv/example_heuristics/__init__.py
fw_heudiconv/example_heuristics/demo.py
fw_heudiconv/example_heuristics/multi-task_fmri.py
fw_heudiconv/example_heuristics/reproin_Upenn.py
fw_heudiconv/testing/__init__.py
fw_heudiconv/testing/data.py
fw_heudiconv-0.2.4.dist-info/LICENSE
fw_heudiconv-0.2.4.dist-info/METADATA
fw_heudiconv-0.2.4.dist-info/WHEEL
fw_heudiconv-0.2.4.dist-info/entry_points.txt
fw_heudiconv-0.2.4.dist-info/top_level.txt
fw_heudiconv-0.2.4.dist-info/RECORD
