Metadata-Version: 2.1
Name: fw-heudiconv
Version: 0.2.4
Summary: Use heudiconv heuristics for BIDS curation on flywheel
Home-page: https://github.com/PennBBL/fw_heudiconv
Author: Tinashe M. Tapera, Matt Cieslak, Harsha Kethineni
Author-email: tinashemtapera@gmail.com
Maintainer: Matt Cieslak, Tinashe M. Tapera
Maintainer-email: Matthew.Cieslak@pennmedicine.upenn.edu
License: 3-clause BSD
Platform: UNKNOWN
Classifier: Programming Language :: Python :: 3.6
Classifier: License :: OSI Approved :: MIT License
Classifier: Operating System :: OS Independent
Requires-Python: >=3.5
Requires-Dist: flywheel-sdk
Requires-Dist: heudiconv
Requires-Dist: pandas
Requires-Dist: bids-validator
